deepcausalmmm/__init__.py
deepcausalmmm/cli.py
deepcausalmmm/exceptions.py
deepcausalmmm/core/__init__.py
deepcausalmmm/core/config.py
deepcausalmmm/core/dag_model.py
deepcausalmmm/core/data.py
deepcausalmmm/core/inference.py
deepcausalmmm/core/scaling.py
deepcausalmmm/core/seasonality.py
deepcausalmmm/core/train_model.py
deepcausalmmm/core/trainer.py
deepcausalmmm/core/unified_model.py
deepcausalmmm/core/visualization.py
deepcausalmmm/postprocess/__init__.py
deepcausalmmm/postprocess/analysis.py
deepcausalmmm/postprocess/comprehensive_analysis.py
deepcausalmmm/postprocess/dag_postprocess.py
deepcausalmmm/postprocess/response_curves.py
deepcausalmmm/utils/__init__.py
deepcausalmmm/utils/data_generator.py
deepcausalmmm/utils/device.py
deepcausalmmm-1.0.18.dist-info/licenses/LICENSE
deepcausalmmm-1.0.18.dist-info/METADATA
deepcausalmmm-1.0.18.dist-info/WHEEL
deepcausalmmm-1.0.18.dist-info/entry_points.txt
deepcausalmmm-1.0.18.dist-info/top_level.txt
deepcausalmmm-1.0.18.dist-info/RECORD
