Metadata-Version: 2.4
Name: deepcausalmmm
Version: 1.0.18
Summary: Causal Deep Learning marketing-mix modeling library with response curves
Author-email: Aditya Puttaparthi Tirumala <puttaparthy.aditya@gmail.com>
License: MIT
Requires-Python: >=3.9
License-File: LICENSE
Requires-Dist: torch>=2.0
Requires-Dist: pandas>=1.5
Requires-Dist: numpy<2.0,>=1.21
Requires-Dist: plotly>=5.0
Requires-Dist: networkx>=2.6
Requires-Dist: scikit-learn>=1.0
Requires-Dist: scipy>=1.7
Requires-Dist: statsmodels>=0.13
Requires-Dist: tqdm>=4.60
Provides-Extra: test
Requires-Dist: pytest>=8; extra == "test"
Requires-Dist: pytest-cov; extra == "test"
Dynamic: license-file
